{"1646159558680.jpg": {"squad": [{"name": "char_128_plosis", "skill": 2}, {"name": "char_486_takila", "skill": 2}, {"name": "char_274_astesi", "skill": 2}, {"name": "char_158_milu", "skill": 2}, {"name": "char_415_flint", "skill": 2}, {"name": "char_173_slchan", "skill": 2}, {"name": "char_222_bpipe", "skill": 3}, {"name": "char_115_headbr", "skill": 1}, {"name": "char_151_myrtle", "skill": 1}, {"name": "char_188_helage", "skill": 2}, {"name": "char_133_mm", "skill": 2}, {"name": "char_102_texas", "skill": 2}], "group": 0, "support": {"name": null}, "risk": 18, "avgRarity": 5.0, "opcount": 12, "soul": 89.47}, "1646167767356.jpg": {"squad": [{"name": "char_179_cgbird", "skill": 3}, {"name": "char_151_myrtle", "skill": 1}, {"name": "char_171_bldsk", "skill": 2}, {"name": "char_358_lisa", "skill": 3}, {"name": "char_350_surtr", "skill": 3}, {"name": "char_401_elysm", "skill": 2}, {"name": "char_202_demkni", "skill": 3}, {"name": "char_311_mudrok", "skill": 3}, {"name": "char_195_glassb", "skill": 1}, {"name": "char_102_texas", "skill": 2}, {"name": "char_180_amgoat", "skill": 3}, {"name": "char_1013_chen2", "skill": 3}, {"name": "char_196_sunbr", "skill": 2}], "group": 0, "support": {"name": "char_179_cgbird", "skill": 3}, "duplicate_of": "1646180710758.jpg", "risk": 23, "avgRarity": 5.385, "opcount": 13, "soul": 75.94}, "1646167107926.jpg": {"squad": [{"name": "char_103_angel", "skill": 3}, {"name": "char_456_ash", "skill": 2}, {"name": "char_213_mostma", "skill": 3}, {"name": "char_293_thorns", "skill": 3}, {"name": "char_003_kalts", "skill": 3}, {"name": "char_102_texas", "skill": 2}], "group": 0, "support": {"name": null}, "risk": 18, "avgRarity": 5.833, "opcount": 6, "soul": 80.85}, "1646159746505.jpg": {"squad": [{"name": "char_355_ethan", "skill": 2}, {"name": "char_187_ccheal", "skill": 1}, {"name": "char_136_hsguma", "skill": 3}, {"name": "char_180_amgoat", "skill": 3}, {"name": "char_358_lisa", "skill": 2}, {"name": "char_151_myrtle", "skill": 1}, {"name": "char_003_kalts", "skill": 3}], "group": 0, "support": {"name": null}, "risk": 18, "avgRarity": 5.143, "opcount": 7, "soul": 80.38}, "1646165095631.jpg": {"squad": [{"name": "char_1012_skadi2", "skill": 2}, {"name": "char_291_aglina", "skill": 3}, {"name": "char_258_podego", "skill": 2}, {"name": "char_242_otter", "skill": 2}], "group": 0, "support": {"name": null}, "risk": 18, "avgRarity": 5.25, "opcount": 4, "soul": 89.09}, "1646157560692.jpg": {"squad": [{"name": "char_401_elysm", "skill": 1}, {"name": "char_003_kalts", "skill": 3}, {"name": "char_456_ash", "skill": 2}, {"name": "char_293_thorns", "skill": 3}, {"name": "char_1012_skadi2", "skill": 2}, {"name": "char_179_cgbird", "skill": 3}, {"name": "char_222_bpipe", "skill": 3}, {"name": "char_1001_amiya2", "skill": 1}], "group": 0, "support": {"name": null}, "risk": 19, "avgRarity": 5.75, "opcount": 8, "soul": 76.9}, "1646164469072.jpg": {"squad": [{"name": "char_180_amgoat", "skill": 3}, {"name": "char_291_aglina", "skill": 3}, {"name": "char_128_plosis", "skill": 1}, {"name": "char_136_hsguma", "skill": 3}, {"name": "char_274_astesi", "skill": 2}, {"name": "char_151_myrtle", "skill": 1}, {"name": "char_003_kalts", "skill": 3}], "group": 0, "support": {"name": "char_180_amgoat", "skill": 3}, "risk": 18, "avgRarity": 5.429, "opcount": 7, "soul": 76.84}, "1646131485278.jpg": {"squad": [{"name": "char_1013_chen2", "skill": 3}, {"name": "char_423_blemsh", "skill": 2}, {"name": "char_128_plosis", "skill": 2}, {"name": "char_344_beewax", "skill": 2}, {"name": "char_151_myrtle", "skill": 1}, {"name": "char_365_aprl", "skill": 2}, {"name": "char_180_amgoat", "skill": 3}], "group": 0, "support": {"name": "char_1013_chen2", "skill": 3}, "risk": 18, "avgRarity": 5.286, "opcount": 7, "soul": 81.9}, "1646170238698.jpg": {"squad": [{"name": "char_358_lisa", "skill": 3}, {"name": "char_180_amgoat", "skill": 3}, {"name": "char_179_cgbird", "skill": 3}, {"name": "char_003_kalts", "skill": 3}, {"name": "char_102_texas", "skill": 2}, {"name": "char_293_thorns", "skill": 3}, {"name": "char_151_myrtle", "skill": 1}], "group": 0, "support": {"name": null}, "duplicate_of": "1646173595711.jpg", "risk": 19, "avgRarity": 5.571, "opcount": 7, "soul": 59.93}, "1646170002102.jpg": {"squad": [{"name": "char_293_thorns", "skill": 3}, {"name": "char_237_gravel", "skill": 2}, {"name": "char_311_mudrok", "skill": 2}, {"name": "char_103_angel", "skill": 3}, {"name": "char_003_kalts", "skill": 3}, {"name": "char_358_lisa", "skill": 3}, {"name": "char_350_surtr", "skill": 3}], "group": 0, "support": {"name": "char_293_thorns", "skill": 3}, "duplicate_of": "1646176565819.jpg", "risk": 18, "avgRarity": 5.714, "opcount": 7, "soul": 78.96}, "1646171743927.jpg": {"squad": [{"name": "char_500_noirc", "skill": 0}, {"name": "char_123_fang", "skill": 1}, {"name": "char_148_nearl", "skill": 1}, {"name": "char_358_lisa", "skill": 2}, {"name": "char_222_bpipe", "skill": 2}, {"name": "char_326_glacus", "skill": 2}, {"name": "char_151_myrtle", "skill": 1}, {"name": "char_180_amgoat", "skill": 3}, {"name": "char_144_red", "skill": 2}, {"name": "char_502_nblade", "skill": 0}, {"name": "char_298_susuro", "skill": 2}, {"name": "char_225_haak", "skill": 1}], "group": 0, "support": {"name": null}, "duplicate_of": "1646180858162.jpg", "risk": 18, "avgRarity": 4.5, "opcount": 12, "soul": 89.76}, "1646173595711.jpg": {"squad": [{"name": "char_358_lisa", "skill": 3}, {"name": "char_180_amgoat", "skill": 3}, {"name": "char_179_cgbird", "skill": 3}, {"name": "char_003_kalts", "skill": 3}, {"name": "char_144_red", "skill": 2}, {"name": "char_293_thorns", "skill": 3}, {"name": "char_151_myrtle", "skill": 1}], "group": 0, "support": {"name": null}, "risk": 20, "avgRarity": 5.571, "opcount": 7, "soul": 67.9}, "1646170783272.jpg": {"squad": [{"name": "char_1012_skadi2", "skill": 2}, {"name": "char_358_lisa", "skill": 3}, {"name": "char_003_kalts", "skill": 3}, {"name": "char_311_mudrok", "skill": 3}, {"name": "char_202_demkni", "skill": 3}, {"name": "char_180_amgoat", "skill": 3}, {"name": "char_222_bpipe", "skill": 3}, {"name": "char_128_plosis", "skill": 2}, {"name": "char_151_myrtle", "skill": 1}, {"name": "char_472_pasngr", "skill": 3}], "group": 0, "support": {"name": null}, "risk": 20, "avgRarity": 5.7, "opcount": 10, "soul": 71.66}, "1646172591464.jpg": {"squad": [{"name": "char_103_angel", "skill": 3}, {"name": "char_172_svrash", "skill": 3}, {"name": "char_003_kalts", "skill": 3}, {"name": "char_222_bpipe", "skill": 2}, {"name": "char_151_myrtle", "skill": 1}, {"name": "char_143_ghost", "skill": 2}, {"name": "char_350_surtr", "skill": 3}], "group": 0, "support": {"name": "char_103_angel", "skill": 3}, "risk": 18, "avgRarity": 5.571, "opcount": 7, "soul": 69.06}, "1646174511815.jpg": {"squad": [{"name": "char_362_saga", "skill": 3}, {"name": "char_286_cast3", "skill": 0}, {"name": "char_222_bpipe", "skill": 3}, {"name": "char_213_mostma", "skill": 2}, {"name": "char_311_mudrok", "skill": 3}, {"name": "char_474_glady", "skill": 2}, {"name": "char_456_ash", "skill": 2}, {"name": "char_202_demkni", "skill": 1}, {"name": "char_214_kafka", "skill": 1}, {"name": "char_003_kalts", "skill": 3}, {"name": "char_151_myrtle", "skill": 1}, {"name": "char_172_svrash", "skill": 3}, {"name": "char_219_meteo", "skill": 1}], "group": 0, "support": {"name": "char_362_saga", "skill": 3}, "risk": 21, "avgRarity": 5.308, "opcount": 13, "soul": 83.95}, "1646170325268.jpg": {"squad": [{"name": "char_180_amgoat", "skill": 3}, {"name": "char_1013_chen2", "skill": 3}, {"name": "char_151_myrtle", "skill": 1}, {"name": "char_401_elysm", "skill": 1}, {"name": "char_202_demkni", "skill": 2}, {"name": "char_133_mm", "skill": 1}, {"name": "char_003_kalts", "skill": 3}], "group": 0, "support": {"name": "char_180_amgoat", "skill": 3}, "risk": 18, "avgRarity": 5.286, "opcount": 7, "soul": 67.17}, "1646173797824.jpg": {"squad": [{"name": "char_350_surtr", "skill": 3}, {"name": "char_172_svrash", "skill": 3}, {"name": "char_151_myrtle", "skill": 1}, {"name": "char_003_kalts", "skill": 3}, {"name": "char_202_demkni", "skill": 3}, {"name": "char_1013_chen2", "skill": 3}, {"name": "char_423_blemsh", "skill": 2}], "group": 0, "support": {"name": null}, "risk": 18, "avgRarity": 5.714, "opcount": 7, "soul": 69.99}, "1646174618482.jpg": {"squad": [{"name": "char_179_cgbird", "skill": 3}, {"name": "char_151_myrtle", "skill": 1}, {"name": "char_1013_chen2", "skill": 3}, {"name": "char_362_saga", "skill": 3}, {"name": "char_128_plosis", "skill": 2}, {"name": "char_254_vodfox", "skill": 2}, {"name": "char_1012_skadi2", "skill": 2}, {"name": "char_180_amgoat", "skill": 3}, {"name": "char_378_asbest", "skill": 1}, {"name": "char_456_ash", "skill": 2}], "group": 0, "support": {"name": "char_179_cgbird", "skill": 3}, "duplicate_of": "1646184319237.jpg", "risk": 21, "avgRarity": 5.5, "opcount": 10, "soul": 77.75}, "1646176565819.jpg": {"squad": [{"name": "char_293_thorns", "skill": 3}, {"name": "char_1001_amiya2", "skill": 1}, {"name": "char_151_myrtle", "skill": 1}, {"name": "char_237_gravel", "skill": 2}, {"name": "char_311_mudrok", "skill": 2}, {"name": "char_172_svrash", "skill": 3}, {"name": "char_1013_chen2", "skill": 3}, {"name": "char_103_angel", "skill": 3}, {"name": "char_003_kalts", "skill": 3}, {"name": "char_2014_nian", "skill": 2}, {"name": "char_298_susuro", "skill": 2}, {"name": "char_358_lisa", "skill": 3}, {"name": "char_350_surtr", "skill": 3}], "group": 0, "support": {"name": "char_293_thorns", "skill": 3}, "risk": 20, "avgRarity": 5.462, "opcount": 13, "soul": 80.58}, "1646175374894.jpg": {"squad": [{"name": "char_143_ghost", "skill": 2}, {"name": "char_218_cuttle", "skill": 1}, {"name": "char_263_skadi", "skill": 3}, {"name": "char_474_glady", "skill": 3}], "group": 0, "support": {"name": null}, "risk": 18, "avgRarity": 5.5, "opcount": 4, "soul": 95.26}, "1646178741142.jpg": {"squad": [{"name": "char_358_lisa", "skill": 3}, {"name": "char_202_demkni", "skill": 3}, {"name": "char_222_bpipe", "skill": 3}, {"name": "char_1013_chen2", "skill": 3}, {"name": "char_151_myrtle", "skill": 1}, {"name": "char_180_amgoat", "skill": 3}, {"name": "char_003_kalts", "skill": 3}], "group": 0, "support": {"name": "char_358_lisa", "skill": 3}, "risk": 18, "avgRarity": 5.714, "opcount": 7, "soul": 54.97}, "1646178986062.jpg": {"squad": [{"name": "char_293_thorns", "skill": 3}, {"name": "char_362_saga", "skill": 3}, {"name": "char_474_glady", "skill": 2}, {"name": "char_222_bpipe", "skill": 3}, {"name": "char_003_kalts", "skill": 3}, {"name": "char_347_jaksel", "skill": 2}, {"name": "char_151_myrtle", "skill": 1}, {"name": "char_102_texas", "skill": 2}, {"name": "char_456_ash", "skill": 2}, {"name": "char_2013_cerber", "skill": 2}, {"name": "char_261_sddrag", "skill": 2}, {"name": "char_1013_chen2", "skill": 3}, {"name": "char_343_tknogi", "skill": 1}], "group": 0, "support": {"name": "char_293_thorns", "skill": 3}, "risk": 19, "avgRarity": 5.462, "opcount": 13, "soul": 83.65}, "1646167957961.jpg": {"squad": [{"name": "char_472_pasngr", "skill": 3}, {"name": "char_151_myrtle", "skill": 1}, {"name": "char_103_angel", "skill": 3}, {"name": "char_1013_chen2", "skill": 3}, {"name": "char_264_f12yin", "skill": 2}, {"name": "char_222_bpipe", "skill": 3}, {"name": "char_003_kalts", "skill": 3}, {"name": "char_102_texas", "skill": 2}, {"name": "char_293_thorns", "skill": 3}, {"name": "char_350_surtr", "skill": 3}], "group": 0, "support": {"name": "char_472_pasngr", "skill": 3}, "risk": 19, "avgRarity": 5.7, "opcount": 10, "soul": 75.11}, "1646179088768.jpg": {"squad": [{"name": "char_264_f12yin", "skill": 2}, {"name": "char_143_ghost", "skill": 2}, {"name": "char_350_surtr", "skill": 3}, {"name": "char_222_bpipe", "skill": 3}, {"name": "char_179_cgbird", "skill": 3}, {"name": "char_172_svrash", "skill": 3}, {"name": "char_401_elysm", "skill": 1}, {"name": "char_1013_chen2", "skill": 3}, {"name": "char_003_kalts", "skill": 3}, {"name": "char_147_shining", "skill": 3}], "group": 0, "support": {"name": "char_264_f12yin", "skill": 2}, "risk": 18, "avgRarity": 5.8, "opcount": 10, "soul": 80.3}, "1646176277925.jpg": {"squad": [{"name": "char_003_kalts", "skill": 3}, {"name": "char_128_plosis", "skill": 2}, {"name": "char_401_elysm", "skill": 1}, {"name": "char_180_amgoat", "skill": 3}, {"name": "char_311_mudrok", "skill": 2}, {"name": "char_102_texas", "skill": 1}, {"name": "char_1013_chen2", "skill": 3}], "group": 0, "support": {"name": "char_003_kalts", "skill": 3}, "risk": 18, "avgRarity": 5.571, "opcount": 7, "soul": 68.42}, "1646179241267.jpg": {"squad": [{"name": "char_293_thorns", "skill": 3}, {"name": "char_401_elysm", "skill": 1}, {"name": "char_1001_amiya2", "skill": 2}, {"name": "char_202_demkni", "skill": 1}, {"name": "char_222_bpipe", "skill": 3}, {"name": "char_151_myrtle", "skill": 1}, {"name": "char_003_kalts", "skill": 3}, {"name": "char_214_kafka", "skill": 1}, {"name": "char_179_cgbird", "skill": 3}, {"name": "char_172_svrash", "skill": 3}], "group": 0, "support": {"name": "char_293_thorns", "skill": 3}, "risk": 19, "avgRarity": 5.5, "opcount": 10, "soul": 74.19}, "1646179795984.jpg": {"squad": [{"name": "char_128_plosis", "skill": 2}, {"name": "char_151_myrtle", "skill": 1}, {"name": "char_202_demkni", "skill": 1}, {"name": "char_401_elysm", "skill": 1}, {"name": "char_003_kalts", "skill": 3}, {"name": "char_180_amgoat", "skill": 3}, {"name": "char_391_rosmon", "skill": 3}], "group": 0, "support": {"name": "char_128_plosis", "skill": 2}, "risk": 22, "avgRarity": 5.429, "opcount": 7, "soul": 68.99}, "1646180858162.jpg": {"squad": [{"name": "char_102_texas", "skill": 2}, {"name": "char_500_noirc", "skill": 0}, {"name": "char_202_demkni", "skill": 1}, {"name": "char_358_lisa", "skill": 2}, {"name": "char_222_bpipe", "skill": 2}, {"name": "char_291_aglina", "skill": 1}, {"name": "char_151_myrtle", "skill": 1}, {"name": "char_180_amgoat", "skill": 3}, {"name": "char_144_red", "skill": 2}, {"name": "char_502_nblade", "skill": 0}, {"name": "char_298_susuro", "skill": 2}, {"name": "char_225_haak", "skill": 1}], "group": 0, "support": {"name": null}, "risk": 19, "avgRarity": 4.833, "opcount": 12, "soul": 83.9}, "1646180239410.jpg": {"squad": [{"name": "char_237_gravel", "skill": 2}, {"name": "char_179_cgbird", "skill": 3}, {"name": "char_199_yak", "skill": 2}, {"name": "char_258_podego", "skill": 2}, {"name": "char_180_amgoat", "skill": 3}, {"name": "char_358_lisa", "skill": 2}, {"name": "char_151_myrtle", "skill": 1}], "group": 0, "support": {"name": null}, "duplicate_of": "1646218985564.jpg", "risk": 18, "avgRarity": 4.857, "opcount": 7, "soul": 79.79}, "1646179527775.jpg": {"squad": [{"name": "char_350_surtr", "skill": 3}, {"name": "char_222_bpipe", "skill": 3}, {"name": "char_291_aglina", "skill": 2}, {"name": "char_358_lisa", "skill": 3}, {"name": "char_401_elysm", "skill": 1}, {"name": "char_136_hsguma", "skill": 3}, {"name": "char_1012_skadi2", "skill": 2}, {"name": "char_102_texas", "skill": 2}, {"name": "char_180_amgoat", "skill": 3}, {"name": "char_179_cgbird", "skill": 3}, {"name": "char_134_ifrit", "skill": 3}, {"name": "char_151_myrtle", "skill": 1}, {"name": "char_213_mostma", "skill": 2}], "group": 0, "support": {"name": "char_350_surtr", "skill": 3}, "duplicate_of": "1646188752379.jpg", "risk": 18, "avgRarity": 5.692, "opcount": 13, "soul": 76.6}, "1646181108426.jpg": {"squad": [{"name": "char_151_myrtle", "skill": 1}, {"name": "char_254_vodfox", "skill": 2}, {"name": "char_196_sunbr", "skill": 1}, {"name": "char_281_popka", "skill": 1}, {"name": "char_180_amgoat", "skill": 3}, {"name": "char_298_susuro", "skill": 2}, {"name": "char_358_lisa", "skill": 2}], "group": 0, "support": {"name": null}, "duplicate_of": "1646233583413.jpg", "risk": 18, "avgRarity": 4.571, "opcount": 7, "soul": 84.89}, "1646179638827.jpg": {"squad": [{"name": "char_172_svrash", "skill": 3}, {"name": "char_311_mudrok", "skill": 2}, {"name": "char_143_ghost", "skill": 2}, {"name": "char_003_kalts", "skill": 3}, {"name": "char_222_bpipe", "skill": 3}, {"name": "char_1013_chen2", "skill": 3}, {"name": "char_401_elysm", "skill": 1}, {"name": "char_128_plosis", "skill": 2}, {"name": "char_293_thorns", "skill": 3}, {"name": "char_144_red", "skill": 2}, {"name": "char_340_shwaz", "skill": 3}, {"name": "char_151_myrtle", "skill": 1}, {"name": "char_456_ash", "skill": 2}], "group": 0, "support": {"name": "char_172_svrash", "skill": 3}, "risk": 18, "avgRarity": 5.538, "opcount": 13, "soul": 75.13}, "1646182746672.jpg": {"squad": [{"name": "char_222_bpipe", "skill": 3}, {"name": "char_311_mudrok", "skill": 3}, {"name": "char_002_amiya", "skill": 3}, {"name": "char_107_liskam", "skill": 2}, {"name": "char_426_billro", "skill": 3}, {"name": "char_147_shining", "skill": 1}, {"name": "char_416_zumama", "skill": 3}, {"name": "char_349_chiave", "skill": 2}, {"name": "char_112_siege", "skill": 2}, {"name": "char_151_myrtle", "skill": 1}, {"name": "char_179_cgbird", "skill": 3}, {"name": "char_174_slbell", "skill": 2}, {"name": "char_376_therex", "skill": 0}], "group": 0, "support": {"name": "char_222_bpipe", "skill": 3}, "risk": 19, "avgRarity": 5.154, "opcount": 13, "soul": 89.73}, "1646181742635.jpg": {"squad": [{"name": "char_222_bpipe", "skill": 3}, {"name": "char_350_surtr", "skill": 3}, {"name": "char_179_cgbird", "skill": 3}, {"name": "char_003_kalts", "skill": 3}, {"name": "char_401_elysm", "skill": 1}, {"name": "char_103_angel", "skill": 3}, {"name": "char_311_mudrok", "skill": 3}], "group": 0, "support": {"name": null}, "duplicate_of": "1646183340577.jpg", "risk": 18, "avgRarity": 5.857, "opcount": 7, "soul": 70.26}, "1646181807667.jpg": {"squad": [{"name": "char_103_angel", "skill": 3}, {"name": "char_222_bpipe", "skill": 3}, {"name": "char_003_kalts", "skill": 3}, {"name": "char_151_myrtle", "skill": 1}, {"name": "char_350_surtr", "skill": 3}, {"name": "char_108_silent", "skill": 2}, {"name": "char_291_aglina", "skill": 3}], "group": 0, "support": {"name": "char_103_angel", "skill": 3}, "risk": 19, "avgRarity": 5.571, "opcount": 7, "soul": 73.43}, "1646182989634.jpg": {"squad": [{"name": "char_401_elysm", "skill": 2}, {"name": "char_291_aglina", "skill": 3}, {"name": "char_1012_skadi2", "skill": 2}, {"name": "char_2013_cerber", "skill": 2}, {"name": "char_215_mantic", "skill": 1}, {"name": "char_340_shwaz", "skill": 3}, {"name": "char_179_cgbird", "skill": 3}, {"name": "char_362_saga", "skill": 3}, {"name": "char_134_ifrit", "skill": 3}, {"name": "char_416_zumama", "skill": 3}, {"name": "char_311_mudrok", "skill": 3}, {"name": "char_151_myrtle", "skill": 1}, {"name": "char_222_bpipe", "skill": 3}], "group": 0, "support": {"name": "char_401_elysm", "skill": 2}, "risk": 20, "avgRarity": 5.692, "opcount": 13, "soul": 82.47}, "1646180710758.jpg": {"squad": [{"name": "char_179_cgbird", "skill": 3}, {"name": "char_151_myrtle", "skill": 1}, {"name": "char_202_demkni", "skill": 3}, {"name": "char_311_mudrok", "skill": 3}, {"name": "char_115_headbr", "skill": 2}, {"name": "char_401_elysm", "skill": 2}, {"name": "char_180_amgoat", "skill": 3}, {"name": "char_1013_chen2", "skill": 3}, {"name": "char_195_glassb", "skill": 1}, {"name": "char_171_bldsk", "skill": 2}, {"name": "char_358_lisa", "skill": 3}, {"name": "char_350_surtr", "skill": 3}, {"name": "char_196_sunbr", "skill": 2}], "group": 0, "support": {"name": "char_179_cgbird", "skill": 3}, "risk": 23, "avgRarity": 5.385, "opcount": 13, "soul": 78.11}, "1646181290141.jpg": {"squad": [{"name": "char_103_angel", "skill": 3}, {"name": "char_1013_chen2", "skill": 3}, {"name": "char_1012_skadi2", "skill": 2}, {"name": "char_003_kalts", "skill": 3}, {"name": "char_452_bstalk", "skill": 1}, {"name": "char_311_mudrok", "skill": 3}], "group": 0, "support": {"name": "char_103_angel", "skill": 3}, "risk": 18, "avgRarity": 5.667, "opcount": 6, "soul": 81.72}, "1646183340577.jpg": {"squad": [{"name": "char_401_elysm", "skill": 1}, {"name": "char_103_angel", "skill": 3}, {"name": "char_222_bpipe", "skill": 3}, {"name": "char_003_kalts", "skill": 3}, {"name": "char_179_cgbird", "skill": 3}, {"name": "char_311_mudrok", "skill": 3}], "group": 0, "support": {"name": null}, "risk": 18, "avgRarity": 5.833, "opcount": 6, "soul": 69.76}, "1646183361222.jpg": {"squad": [{"name": "char_391_rosmon", "skill": 3}, {"name": "char_1013_chen2", "skill": 3}, {"name": "char_340_shwaz", "skill": 3}, {"name": "char_456_ash", "skill": 2}, {"name": "char_197_poca", "skill": 3}, {"name": "char_113_cqbw", "skill": 1}, {"name": "char_103_angel", "skill": 3}], "group": 0, "support": {"name": "char_391_rosmon", "skill": 3}, "risk": 20, "avgRarity": 6.0, "opcount": 7, "soul": 89.25}, "1646183793013.jpg": {"squad": [{"name": "char_180_amgoat", "skill": 3}, {"name": "char_128_plosis", "skill": 2}, {"name": "char_222_bpipe", "skill": 3}, {"name": "char_358_lisa", "skill": 3}, {"name": "char_003_kalts", "skill": 3}, {"name": "char_151_myrtle", "skill": 1}, {"name": "char_423_blemsh", "skill": 1}], "group": 0, "support": {"name": "char_180_amgoat", "skill": 3}, "risk": 18, "avgRarity": 5.571, "opcount": 7, "soul": 68.71}, "1646183572387.jpg": {"squad": [{"name": "char_128_plosis", "skill": 2}, {"name": "char_196_sunbr", "skill": 1}, {"name": "char_358_lisa", "skill": 2}, {"name": "char_180_amgoat", "skill": 3}], "group": 0, "support": {"name": null}, "risk": 18, "avgRarity": 5.25, "opcount": 4, "soul": 83.6}, "1646184319237.jpg": {"squad": [{"name": "char_179_cgbird", "skill": 3}, {"name": "char_180_amgoat", "skill": 3}, {"name": "char_151_myrtle", "skill": 1}, {"name": "char_362_saga", "skill": 3}, {"name": "char_378_asbest", "skill": 1}, {"name": "char_128_plosis", "skill": 2}, {"name": "char_1012_skadi2", "skill": 2}, {"name": "char_254_vodfox", "skill": 2}, {"name": "char_1013_chen2", "skill": 3}, {"name": "char_456_ash", "skill": 2}], "group": 0, "support": {"name": "char_179_cgbird", "skill": 3}, "risk": 22, "avgRarity": 5.5, "opcount": 10, "soul": 77.75}, "1646185115541.jpg": {"squad": [{"name": "char_358_lisa", "skill": 3}, {"name": "char_202_demkni", "skill": 3}, {"name": "char_222_bpipe", "skill": 3}, {"name": "char_1013_chen2", "skill": 3}, {"name": "char_151_myrtle", "skill": 1}, {"name": "char_180_amgoat", "skill": 3}, {"name": "char_003_kalts", "skill": 3}], "group": 0, "support": {"name": "char_358_lisa", "skill": 3}, "duplicate_of": "1646224437733.jpg", "risk": 20, "avgRarity": 5.714, "opcount": 7, "soul": 54.97}, "1646188752379.jpg": {"squad": [{"name": "char_350_surtr", "skill": 3}, {"name": "char_222_bpipe", "skill": 3}, {"name": "char_291_aglina", "skill": 2}, {"name": "char_358_lisa", "skill": 3}, {"name": "char_401_elysm", "skill": 1}, {"name": "char_136_hsguma", "skill": 3}, {"name": "char_1012_skadi2", "skill": 2}, {"name": "char_102_texas", "skill": 2}, {"name": "char_180_amgoat", "skill": 3}, {"name": "char_179_cgbird", "skill": 3}, {"name": "char_134_ifrit", "skill": 3}, {"name": "char_151_myrtle", "skill": 1}, {"name": "char_213_mostma", "skill": 2}], "group": 0, "support": {"name": "char_350_surtr", "skill": 3}, "risk": 20, "avgRarity": 5.692, "opcount": 13, "soul": 76.6}, "1646185143754.jpg": {"squad": [{"name": "char_180_amgoat", "skill": 3}, {"name": "char_202_demkni", "skill": 3}, {"name": "char_426_billro", "skill": 3}, {"name": "char_179_cgbird", "skill": 3}, {"name": "char_134_ifrit", "skill": 3}, {"name": "char_416_zumama", "skill": 3}, {"name": "char_401_elysm", "skill": 1}, {"name": "char_151_myrtle", "skill": 1}, {"name": "char_358_lisa", "skill": 3}, {"name": "char_112_siege", "skill": 2}], "group": 0, "support": {"name": null}, "duplicate_of": "1646207846230.jpg", "risk": 22, "avgRarity": 5.7, "opcount": 10, "soul": 79.71}, "1646181488898.jpg": {"squad": [{"name": "char_486_takila", "skill": 2}, {"name": "char_144_red", "skill": 2}, {"name": "char_102_texas", "skill": 2}, {"name": "char_158_milu", "skill": 1}, {"name": "char_421_crow", "skill": 2}, {"name": "char_129_bluep", "skill": 2}, {"name": "char_173_slchan", "skill": 2}, {"name": "char_367_swllow", "skill": 2}, {"name": "char_261_sddrag", "skill": 2}, {"name": "char_115_headbr", "skill": 1}, {"name": "char_171_bldsk", "skill": 2}, {"name": "char_143_ghost", "skill": 2}, {"name": "char_401_elysm", "skill": 2}], "group": 0, "support": {"name": "char_486_takila", "skill": 2}, "risk": 20, "avgRarity": 5.0, "opcount": 13, "soul": 93.48}, "1646184030464.jpg": {"squad": [{"name": "char_401_elysm", "skill": 1}, {"name": "char_188_helage", "skill": 2}, {"name": "char_115_headbr", "skill": 2}, {"name": "char_405_absin", "skill": 1}, {"name": "char_003_kalts", "skill": 3}, {"name": "char_196_sunbr", "skill": 1}, {"name": "char_241_panda", "skill": 2}, {"name": "char_197_poca", "skill": 3}, {"name": "char_293_thorns", "skill": 3}, {"name": "char_272_strong", "skill": 2}, {"name": "char_195_glassb", "skill": 1}, {"name": "char_137_brownb", "skill": 1}], "group": 0, "support": {"name": null}, "risk": 18, "avgRarity": 5.083, "opcount": 12, "soul": 93.62}, "1646189011255.jpg": {"squad": [{"name": "char_350_surtr", "skill": 3}, {"name": "char_112_siege", "skill": 2}, {"name": "char_241_panda", "skill": 1}, {"name": "char_151_myrtle", "skill": 1}, {"name": "char_1013_chen2", "skill": 3}, {"name": "char_172_svrash", "skill": 3}, {"name": "char_140_whitew", "skill": 2}, {"name": "char_401_elysm", "skill": 2}, {"name": "char_003_kalts", "skill": 3}, {"name": "char_222_bpipe", "skill": 3}, {"name": "char_202_demkni", "skill": 1}, {"name": "char_143_ghost", "skill": 2}, {"name": "char_236_rope", "skill": 1}], "group": 0, "support": {"name": "char_350_surtr", "skill": 3}, "risk": 18, "avgRarity": 5.385, "opcount": 13, "soul": 82.18}, "1646190583672.jpg": {"squad": [{"name": "char_1013_chen2", "skill": 3}, {"name": "char_222_bpipe", "skill": 3}, {"name": "char_003_kalts", "skill": 3}, {"name": "char_187_ccheal", "skill": 1}, {"name": "char_179_cgbird", "skill": 2}, {"name": "char_2015_dusk", "skill": 2}, {"name": "char_411_tomimi", "skill": 2}, {"name": "char_2014_nian", "skill": 2}, {"name": "char_261_sddrag", "skill": 2}, {"name": "char_202_demkni", "skill": 3}], "group": 0, "support": {"name": "char_1013_chen2", "skill": 3}, "risk": 18, "avgRarity": 5.6, "opcount": 10, "soul": 89.28}, "1646190515687.jpg": {"squad": [{"name": "char_376_therex", "skill": 0}, {"name": "char_144_red", "skill": 2}, {"name": "char_158_milu", "skill": 2}, {"name": "char_129_bluep", "skill": 1}, {"name": "char_171_bldsk", "skill": 2}, {"name": "char_2014_nian", "skill": 2}, {"name": "char_340_shwaz", "skill": 3}, {"name": "char_220_grani", "skill": 2}, {"name": "char_1001_amiya2", "skill": 2}, {"name": "char_437_mizuki", "skill": 2}, {"name": "char_391_rosmon", "skill": 2}, {"name": "char_362_saga", "skill": 3}], "group": 0, "support": {"name": null}, "duplicate_of": "1646198674471.jpg", "risk": 18, "avgRarity": 5.083, "opcount": 12, "soul": 94.71}, "1646189234558.jpg": {"squad": [{"name": "char_180_amgoat", "skill": 3}, {"name": "char_381_bubble", "skill": 2}, {"name": "char_117_myrrh", "skill": 1}, {"name": "char_254_vodfox", "skill": 2}, {"name": "char_214_kafka", "skill": 1}, {"name": "char_196_sunbr", "skill": 1}, {"name": "char_298_susuro", "skill": 2}, {"name": "char_281_popka", "skill": 1}, {"name": "char_151_myrtle", "skill": 1}, {"name": "char_258_podego", "skill": 2}, {"name": "char_190_clour", "skill": 2}, {"name": "char_358_lisa", "skill": 2}], "group": 0, "support": {"name": null}, "duplicate_of": "1646233583413.jpg", "risk": 19, "avgRarity": 4.417, "opcount": 12, "soul": 90.83}, "1646192421808.jpg": {"squad": [{"name": "char_128_plosis", "skill": 2}, {"name": "char_401_elysm", "skill": 1}, {"name": "char_003_kalts", "skill": 3}, {"name": "char_180_amgoat", "skill": 3}, {"name": "char_222_bpipe", "skill": 3}, {"name": "char_202_demkni", "skill": 1}, {"name": "char_358_lisa", "skill": 2}], "group": 0, "support": {"name": null}, "risk": 20, "avgRarity": 5.714, "opcount": 7, "soul": 68.52}, "1646188884983.jpg": {"squad": [{"name": "char_180_amgoat", "skill": 3}, {"name": "char_128_plosis", "skill": 2}, {"name": "char_2013_cerber", "skill": 2}, {"name": "char_202_demkni", "skill": 1}, {"name": "char_003_kalts", "skill": 3}, {"name": "char_337_utage", "skill": 2}, {"name": "char_151_myrtle", "skill": 1}], "group": 0, "support": {"name": "char_180_amgoat", "skill": 3}, "risk": 19, "avgRarity": 5.286, "opcount": 7, "soul": 76.5}, "1646185257556.jpg": {"squad": [{"name": "char_1012_skadi2", "skill": 2}, {"name": "char_421_crow", "skill": 1}, {"name": "char_003_kalts", "skill": 3}, {"name": "char_222_bpipe", "skill": 2}, {"name": "char_215_mantic", "skill": 1}, {"name": "char_151_myrtle", "skill": 1}, {"name": "char_128_plosis", "skill": 2}, {"name": "char_456_ash", "skill": 2}, {"name": "char_250_phatom", "skill": 2}, {"name": "char_350_surtr", "skill": 3}, {"name": "char_293_thorns", "skill": 3}, {"name": "char_102_texas", "skill": 2}], "group": 0, "support": {"name": null}, "risk": 18, "avgRarity": 5.5, "opcount": 12, "soul": 79.16}, "1646193549276.jpg": {"squad": [{"name": "char_180_amgoat", "skill": 3}, {"name": "char_362_saga", "skill": 3}, {"name": "char_222_bpipe", "skill": 3}, {"name": "char_179_cgbird", "skill": 3}, {"name": "char_1013_chen2", "skill": 3}, {"name": "char_151_myrtle", "skill": 1}, {"name": "char_003_kalts", "skill": 3}], "group": 0, "support": {"name": "char_180_amgoat", "skill": 3}, "risk": 18, "avgRarity": 5.714, "opcount": 7, "soul": 60.46}, "1646195427538.jpg": {"squad": [{"name": "char_456_ash", "skill": 2}, {"name": "char_348_ceylon", "skill": 2}, {"name": "char_248_mgllan", "skill": 1}, {"name": "char_213_mostma", "skill": 3}, {"name": "char_437_mizuki", "skill": 3}, {"name": "char_421_crow", "skill": 2}, {"name": "char_336_folivo", "skill": 2}, {"name": "char_362_saga", "skill": 3}, {"name": "char_1013_chen2", "skill": 3}, {"name": "char_474_glady", "skill": 3}, {"name": "char_151_myrtle", "skill": 1}, {"name": "char_340_shwaz", "skill": 3}, {"name": "char_222_bpipe", "skill": 3}], "group": 0, "support": {"name": "char_456_ash", "skill": 2}, "risk": 20, "avgRarity": 5.615, "opcount": 13, "soul": 88.81}, "1646194809309.jpg": {"squad": [{"name": "char_128_plosis", "skill": 2}, {"name": "char_143_ghost", "skill": 2}, {"name": "char_003_kalts", "skill": 3}, {"name": "char_113_cqbw", "skill": 3}, {"name": "char_362_saga", "skill": 3}, {"name": "char_102_texas", "skill": 2}, {"name": "char_140_whitew", "skill": 2}], "group": 0, "support": {"name": null}, "risk": 19, "avgRarity": 5.429, "opcount": 7, "soul": 87.41}, "1646194196154.jpg": {"squad": [{"name": "char_456_ash", "skill": 2}, {"name": "char_293_thorns", "skill": 3}, {"name": "char_250_phatom", "skill": 2}, {"name": "char_003_kalts", "skill": 3}], "group": 0, "support": {"name": null}, "risk": 18, "avgRarity": 6.0, "opcount": 4, "soul": 82.45}, "1646196576915.jpg": {"squad": [{"name": "char_003_kalts", "skill": 3}, {"name": "char_311_mudrok", "skill": 3}, {"name": "char_350_surtr", "skill": 3}, {"name": "char_180_amgoat", "skill": 3}, {"name": "char_411_tomimi", "skill": 2}, {"name": "char_151_myrtle", "skill": 1}, {"name": "char_179_cgbird", "skill": 1}], "group": 0, "support": {"name": "char_003_kalts", "skill": 3}, "risk": 18, "avgRarity": 5.571, "opcount": 7, "soul": 69.1}, "1646192673250.jpg": {"squad": [{"name": "char_180_amgoat", "skill": 3}, {"name": "char_181_flower", "skill": 2}, {"name": "char_222_bpipe", "skill": 3}, {"name": "char_151_myrtle", "skill": 1}, {"name": "char_350_surtr", "skill": 3}, {"name": "char_003_kalts", "skill": 2}, {"name": "char_426_billro", "skill": 3}], "group": 0, "support": {"name": null}, "risk": 22, "avgRarity": 5.429, "opcount": 7, "soul": 73.67}, "1646193374464.jpg": {"squad": [{"name": "char_003_kalts", "skill": 3}, {"name": "char_128_plosis", "skill": 2}, {"name": "char_180_amgoat", "skill": 3}, {"name": "char_401_elysm", "skill": 1}, {"name": "char_151_myrtle", "skill": 1}, {"name": "char_304_zebra", "skill": 2}, {"name": "char_1013_chen2", "skill": 3}], "group": 0, "support": {"name": "char_003_kalts", "skill": 3}, "risk": 18, "avgRarity": 5.286, "opcount": 7, "soul": 69.67}, "1646196890140.jpg": {"squad": [{"name": "char_202_demkni", "skill": 3}, {"name": "char_143_ghost", "skill": 2}, {"name": "char_1013_chen2", "skill": 3}, {"name": "char_350_surtr", "skill": 3}, {"name": "char_151_myrtle", "skill": 1}, {"name": "char_172_svrash", "skill": 3}, {"name": "char_003_kalts", "skill": 2}], "group": 0, "support": {"name": null}, "risk": 18, "avgRarity": 5.571, "opcount": 7, "soul": 67.06}, "1646197633550.jpg": {"squad": [{"name": "char_401_elysm", "skill": 2}, {"name": "char_102_texas", "skill": 2}, {"name": "char_350_surtr", "skill": 3}, {"name": "char_172_svrash", "skill": 3}, {"name": "char_143_ghost", "skill": 2}, {"name": "char_1013_chen2", "skill": 3}, {"name": "char_474_glady", "skill": 2}, {"name": "char_103_angel", "skill": 3}, {"name": "char_222_bpipe", "skill": 3}, {"name": "char_456_ash", "skill": 2}, {"name": "char_254_vodfox", "skill": 2}, {"name": "char_151_myrtle", "skill": 1}, {"name": "char_171_bldsk", "skill": 2}], "group": 0, "support": {"name": "char_401_elysm", "skill": 2}, "risk": 21, "avgRarity": 5.462, "opcount": 13, "soul": 78.28}, "1646197673687.jpg": {"squad": [{"name": "char_222_bpipe", "skill": 3}, {"name": "char_1013_chen2", "skill": 3}, {"name": "char_1012_skadi2", "skill": 2}, {"name": "char_456_ash", "skill": 2}, {"name": "char_350_surtr", "skill": 3}, {"name": "char_179_cgbird", "skill": 3}, {"name": "char_171_bldsk", "skill": 2}, {"name": "char_197_poca", "skill": 3}, {"name": "char_264_f12yin", "skill": 2}, {"name": "char_151_myrtle", "skill": 1}, {"name": "char_115_headbr", "skill": 2}, {"name": "char_003_kalts", "skill": 3}, {"name": "char_401_elysm", "skill": 2}], "group": 0, "support": {"name": "char_222_bpipe", "skill": 3}, "risk": 18, "avgRarity": 5.615, "opcount": 13, "soul": 77.03}, "1646198570183.jpg": {"squad": [{"name": "char_254_vodfox", "skill": 2}, {"name": "char_222_bpipe", "skill": 3}, {"name": "char_128_plosis", "skill": 2}, {"name": "char_136_hsguma", "skill": 3}, {"name": "char_243_waaifu", "skill": 1}, {"name": "char_151_myrtle", "skill": 1}, {"name": "char_202_demkni", "skill": 3}, {"name": "char_344_beewax", "skill": 1}, {"name": "char_378_asbest", "skill": 2}, {"name": "char_214_kafka", "skill": 1}, {"name": "char_147_shining", "skill": 3}, {"name": "char_426_billro", "skill": 2}, {"name": "char_416_zumama", "skill": 3}], "group": 0, "support": {"name": "char_254_vodfox", "skill": 2}, "duplicate_of": "1646248625295.jpg", "risk": 20, "avgRarity": 5.385, "opcount": 13, "soul": 88.56}, "1646198848811.jpg": {"squad": [{"name": "char_311_mudrok", "skill": 3}, {"name": "char_291_aglina", "skill": 3}, {"name": "char_362_saga", "skill": 2}, {"name": "char_134_ifrit", "skill": 2}, {"name": "char_401_elysm", "skill": 2}, {"name": "char_358_lisa", "skill": 2}, {"name": "char_248_mgllan", "skill": 3}], "group": 0, "support": {"name": null}, "risk": 20, "avgRarity": 5.857, "opcount": 7, "soul": 85.92}, "1646181569617.jpg": {"squad": [{"name": "char_456_ash", "skill": 2}, {"name": "char_423_blemsh", "skill": 3}, {"name": "char_187_ccheal", "skill": 2}, {"name": "char_102_texas", "skill": 2}, {"name": "char_115_headbr", "skill": 2}, {"name": "char_261_sddrag", "skill": 2}, {"name": "char_401_elysm", "skill": 2}, {"name": "char_179_cgbird", "skill": 2}, {"name": "char_457_blitz", "skill": 2}, {"name": "char_416_zumama", "skill": 3}, {"name": "char_250_phatom", "skill": 2}, {"name": "char_140_whitew", "skill": 2}, {"name": "char_003_kalts", "skill": 3}], "group": 0, "support": {"name": "char_456_ash", "skill": 2}, "duplicate_of": "1646235273373.jpg", "risk": 12, "avgRarity": 5.385, "opcount": 13, "soul": 90.3}, "1646198741434.jpg": {"squad": [{"name": "char_151_myrtle", "skill": 1}, {"name": "char_456_ash", "skill": 2}, {"name": "char_222_bpipe", "skill": 3}, {"name": "char_293_thorns", "skill": 3}, {"name": "char_003_kalts", "skill": 3}, {"name": "char_1012_skadi2", "skill": 2}], "group": 0, "support": {"name": null}, "risk": 18, "avgRarity": 5.667, "opcount": 6, "soul": 61.8}, "1646200562872.jpg": {"squad": [{"name": "char_180_amgoat", "skill": 3}, {"name": "char_1013_chen2", "skill": 3}, {"name": "char_151_myrtle", "skill": 1}, {"name": "char_136_hsguma", "skill": 3}, {"name": "char_258_podego", "skill": 2}, {"name": "char_147_shining", "skill": 3}, {"name": "char_291_aglina", "skill": 1}], "group": 0, "support": {"name": "char_180_amgoat", "skill": 3}, "risk": 18, "avgRarity": 5.429, "opcount": 7, "soul": 78.9}, "1646198674471.jpg": {"squad": [{"name": "char_2014_nian", "skill": 2}, {"name": "char_171_bldsk", "skill": 2}, {"name": "char_158_milu", "skill": 2}, {"name": "char_391_rosmon", "skill": 2}, {"name": "char_376_therex", "skill": 0}, {"name": "char_144_red", "skill": 2}, {"name": "char_340_shwaz", "skill": 3}, {"name": "char_220_grani", "skill": 2}, {"name": "char_1001_amiya2", "skill": 2}, {"name": "char_437_mizuki", "skill": 2}, {"name": "char_129_bluep", "skill": 1}, {"name": "char_362_saga", "skill": 3}], "group": 0, "support": {"name": null}, "risk": 18, "avgRarity": 5.083, "opcount": 12, "soul": 94.71}, "1646201740256.jpg": {"squad": [{"name": "char_222_bpipe", "skill": 3}, {"name": "char_456_ash", "skill": 2}, {"name": "char_102_texas", "skill": 2}, {"name": "char_311_mudrok", "skill": 3}, {"name": "char_436_whispr", "skill": 2}, {"name": "char_254_vodfox", "skill": 2}, {"name": "char_426_billro", "skill": 3}, {"name": "char_151_myrtle", "skill": 1}, {"name": "char_365_aprl", "skill": 2}, {"name": "char_003_kalts", "skill": 3}], "group": 0, "support": {"name": "char_222_bpipe", "skill": 3}, "risk": 18, "avgRarity": 5.4, "opcount": 10, "soul": 81.45}, "1646200884266.jpg": {"squad": [{"name": "char_332_archet", "skill": 3}, {"name": "char_350_surtr", "skill": 3}, {"name": "char_144_red", "skill": 2}, {"name": "char_151_myrtle", "skill": 1}, {"name": "char_250_phatom", "skill": 2}, {"name": "char_423_blemsh", "skill": 2}, {"name": "char_003_kalts", "skill": 3}], "group": 0, "support": {"name": "char_332_archet", "skill": 3}, "risk": 18, "avgRarity": 5.571, "opcount": 7, "soul": 83.43}, "1646202558655.jpg": {"squad": [{"name": "char_172_svrash", "skill": 3}, {"name": "char_401_elysm", "skill": 2}, {"name": "char_311_mudrok", "skill": 2}, {"name": "char_102_texas", "skill": 2}, {"name": "char_2013_cerber", "skill": 2}, {"name": "char_003_kalts", "skill": 3}, {"name": "char_1012_skadi2", "skill": 2}, {"name": "char_180_amgoat", "skill": 3}, {"name": "char_358_lisa", "skill": 3}, {"name": "char_222_bpipe", "skill": 3}, {"name": "char_151_myrtle", "skill": 1}, {"name": "char_134_ifrit", "skill": 3}, {"name": "char_179_cgbird", "skill": 3}], "group": 0, "support": {"name": "char_172_svrash", "skill": 3}, "risk": 18, "avgRarity": 5.692, "opcount": 13, "soul": 72.94}, "1646204291107.jpg": {"squad": [{"name": "char_264_f12yin", "skill": 2}, {"name": "char_136_hsguma", "skill": 3}, {"name": "char_103_angel", "skill": 3}, {"name": "char_401_elysm", "skill": 1}, {"name": "char_171_bldsk", "skill": 1}, {"name": "char_003_kalts", "skill": 3}, {"name": "char_222_bpipe", "skill": 3}, {"name": "char_293_thorns", "skill": 3}, {"name": "char_151_myrtle", "skill": 1}], "group": 0, "support": {"name": "char_264_f12yin", "skill": 2}, "risk": 18, "avgRarity": 5.556, "opcount": 9, "soul": 77.09}, "1646200778876.jpg": {"squad": [{"name": "char_147_shining", "skill": 3}, {"name": "char_201_moeshd", "skill": 1}, {"name": "char_291_aglina", "skill": 3}, {"name": "char_148_nearl", "skill": 1}, {"name": "char_311_mudrok", "skill": 3}, {"name": "char_134_ifrit", "skill": 3}, {"name": "char_1013_chen2", "skill": 3}], "group": 0, "support": {"name": "char_147_shining", "skill": 3}, "risk": 18, "avgRarity": 5.714, "opcount": 7, "soul": 89.71}, "1646205279258.jpg": {"squad": [{"name": "char_115_headbr", "skill": 1}, {"name": "char_2013_cerber", "skill": 2}, {"name": "char_151_myrtle", "skill": 1}, {"name": "char_222_bpipe", "skill": 3}, {"name": "char_179_cgbird", "skill": 3}, {"name": "char_401_elysm", "skill": 2}, {"name": "char_102_texas", "skill": 2}, {"name": "char_134_ifrit", "skill": 3}, {"name": "char_202_demkni", "skill": 3}, {"name": "char_180_amgoat", "skill": 3}, {"name": "char_286_cast3", "skill": 0}, {"name": "char_358_lisa", "skill": 3}, {"name": "char_311_mudrok", "skill": 3}], "group": 0, "support": {"name": "char_115_headbr", "skill": 1}, "risk": 25, "avgRarity": 5.231, "opcount": 13, "soul": 78.27}, "1646206031853.jpg": {"squad": [{"name": "char_456_ash", "skill": 2}, {"name": "char_172_svrash", "skill": 3}, {"name": "char_151_myrtle", "skill": 1}, {"name": "char_293_thorns", "skill": 3}, {"name": "char_003_kalts", "skill": 3}], "group": 0, "support": {"name": null}, "risk": 18, "avgRarity": 5.6, "opcount": 5, "soul": 63.76}, "1646206583134.jpg": {"squad": [{"name": "char_179_cgbird", "skill": 3}, {"name": "char_358_lisa", "skill": 3}, {"name": "char_172_svrash", "skill": 3}, {"name": "char_340_shwaz", "skill": 3}, {"name": "char_291_aglina", "skill": 2}, {"name": "char_202_demkni", "skill": 3}, {"name": "char_222_bpipe", "skill": 3}, {"name": "char_401_elysm", "skill": 1}, {"name": "char_1013_chen2", "skill": 3}, {"name": "char_102_texas", "skill": 2}, {"name": "char_151_myrtle", "skill": 1}, {"name": "char_180_amgoat", "skill": 3}, {"name": "char_311_mudrok", "skill": 3}], "group": 0, "support": {"name": "char_179_cgbird", "skill": 3}, "risk": 25, "avgRarity": 5.692, "opcount": 13, "soul": 69.45}, "1646202116570.jpg": {"squad": [{"name": "char_222_bpipe", "skill": 3}, {"name": "char_311_mudrok", "skill": 3}, {"name": "char_426_billro", "skill": 1}, {"name": "char_179_cgbird", "skill": 3}, {"name": "char_401_elysm", "skill": 1}, {"name": "char_358_lisa", "skill": 2}, {"name": "char_171_bldsk", "skill": 2}, {"name": "char_350_surtr", "skill": 3}, {"name": "char_151_myrtle", "skill": 1}, {"name": "char_134_ifrit", "skill": 2}], "group": 0, "support": {"name": null}, "risk": 18, "avgRarity": 5.6, "opcount": 10, "soul": 75.89}, "1646207846230.jpg": {"squad": [{"name": "char_358_lisa", "skill": 3}, {"name": "char_401_elysm", "skill": 1}, {"name": "char_151_myrtle", "skill": 1}, {"name": "char_426_billro", "skill": 3}, {"name": "char_180_amgoat", "skill": 3}, {"name": "char_202_demkni", "skill": 3}, {"name": "char_416_zumama", "skill": 3}, {"name": "char_179_cgbird", "skill": 3}, {"name": "char_134_ifrit", "skill": 3}, {"name": "char_112_siege", "skill": 2}], "group": 0, "support": {"name": "char_358_lisa", "skill": 3}, "risk": 23, "avgRarity": 5.7, "opcount": 10, "soul": 79.71}, "1646193580678.jpg": {"squad": [{"name": "char_180_amgoat", "skill": 3}, {"name": "char_291_aglina", "skill": 3}, {"name": "char_179_cgbird", "skill": 2}, {"name": "char_136_hsguma", "skill": 3}, {"name": "char_172_svrash", "skill": 3}, {"name": "char_151_myrtle", "skill": 1}, {"name": "char_003_kalts", "skill": 3}], "group": 0, "support": {"name": "char_180_amgoat", "skill": 3}, "risk": 20, "avgRarity": 5.714, "opcount": 7, "soul": 69.88}, "1646208109323.jpg": {"squad": [{"name": "char_222_bpipe", "skill": 3}, {"name": "char_376_therex", "skill": 0}, {"name": "char_115_headbr", "skill": 2}, {"name": "char_179_cgbird", "skill": 3}, {"name": "char_1012_skadi2", "skill": 2}, {"name": "char_151_myrtle", "skill": 1}, {"name": "char_102_texas", "skill": 2}, {"name": "char_311_mudrok", "skill": 3}, {"name": "char_340_shwaz", "skill": 3}, {"name": "char_401_elysm", "skill": 2}, {"name": "char_180_amgoat", "skill": 3}, {"name": "char_358_lisa", "skill": 2}, {"name": "char_332_archet", "skill": 3}], "group": 0, "support": {"name": "char_222_bpipe", "skill": 3}, "risk": 22, "avgRarity": 5.231, "opcount": 13, "soul": 78.27}, "1646211523287.jpg": {"squad": [{"name": "char_456_ash", "skill": 2}, {"name": "char_225_haak", "skill": 3}, {"name": "char_102_texas", "skill": 1}, {"name": "char_003_kalts", "skill": 3}, {"name": "char_172_svrash", "skill": 3}, {"name": "char_171_bldsk", "skill": 2}, {"name": "char_391_rosmon", "skill": 3}, {"name": "char_143_ghost", "skill": 2}, {"name": "char_151_myrtle", "skill": 1}, {"name": "char_128_plosis", "skill": 2}, {"name": "char_1013_chen2", "skill": 3}, {"name": "char_350_surtr", "skill": 3}, {"name": "char_222_bpipe", "skill": 3}], "group": 0, "support": {"name": "char_456_ash", "skill": 2}, "risk": 18, "avgRarity": 5.538, "opcount": 13, "soul": 78.6}, "1646210348597.jpg": {"squad": [{"name": "char_401_elysm", "skill": 1}, {"name": "char_376_therex", "skill": 0}, {"name": "char_202_demkni", "skill": 3}, {"name": "char_291_aglina", "skill": 2}, {"name": "char_1013_chen2", "skill": 3}, {"name": "char_340_shwaz", "skill": 3}, {"name": "char_179_cgbird", "skill": 3}, {"name": "char_311_mudrok", "skill": 3}, {"name": "char_151_myrtle", "skill": 1}, {"name": "char_358_lisa", "skill": 3}, {"name": "char_180_amgoat", "skill": 3}, {"name": "char_222_bpipe", "skill": 3}, {"name": "char_102_texas", "skill": 2}], "group": 0, "support": {"name": "char_401_elysm", "skill": 1}, "risk": 23, "avgRarity": 5.308, "opcount": 13, "soul": 72.28}, "1646211707635.jpg": {"squad": [{"name": "char_195_glassb", "skill": 2}, {"name": "char_179_cgbird", "skill": 3}, {"name": "char_237_gravel", "skill": 2}, {"name": "char_180_amgoat", "skill": 3}, {"name": "char_151_myrtle", "skill": 1}, {"name": "char_202_demkni", "skill": 2}, {"name": "char_291_aglina", "skill": 1}], "group": 0, "support": {"name": null}, "risk": 18, "avgRarity": 5.286, "opcount": 7, "soul": 75.77}, "1646211711989.jpg": {"squad": [{"name": "char_1013_chen2", "skill": 3}, {"name": "char_502_nblade", "skill": 0}, {"name": "char_180_amgoat", "skill": 3}, {"name": "char_102_texas", "skill": 2}, {"name": "char_172_svrash", "skill": 3}, {"name": "char_151_myrtle", "skill": 1}, {"name": "char_202_demkni", "skill": 3}, {"name": "char_1012_skadi2", "skill": 2}, {"name": "char_214_kafka", "skill": 1}, {"name": "char_401_elysm", "skill": 2}, {"name": "char_222_bpipe", "skill": 3}, {"name": "char_179_cgbird", "skill": 3}], "group": 0, "support": {"name": "char_1013_chen2", "skill": 3}, "risk": 18, "avgRarity": 5.25, "opcount": 12, "soul": 74.53}, "1646213687076.jpg": {"squad": [{"name": "char_172_svrash", "skill": 3}, {"name": "char_350_surtr", "skill": 3}, {"name": "char_293_thorns", "skill": 3}, {"name": "char_222_bpipe", "skill": 3}, {"name": "char_151_myrtle", "skill": 1}, {"name": "char_1012_skadi2", "skill": 2}, {"name": "char_401_elysm", "skill": 1}, {"name": "char_103_angel", "skill": 3}, {"name": "char_147_shining", "skill": 3}, {"name": "char_102_texas", "skill": 2}, {"name": "char_003_kalts", "skill": 3}, {"name": "char_486_takila", "skill": 2}], "group": 0, "support": {"name": null}, "risk": 19, "avgRarity": 5.583, "opcount": 12, "soul": 76.01}, "1646211923335.jpg": {"squad": [{"name": "char_293_thorns", "skill": 3}], "group": 0, "support": {"name": "char_293_thorns", "skill": 3}, "risk": 18, "avgRarity": 6.0, "opcount": 1, "soul": 79.05}, "1646213930835.jpg": {"squad": [{"name": "char_003_kalts", "skill": 3}, {"name": "char_143_ghost", "skill": 2}, {"name": "char_103_angel", "skill": 3}, {"name": "char_1012_skadi2", "skill": 2}, {"name": "char_222_bpipe", "skill": 3}, {"name": "char_293_thorns", "skill": 3}, {"name": "char_151_myrtle", "skill": 1}], "group": 0, "support": {"name": "char_003_kalts", "skill": 3}, "risk": 18, "avgRarity": 5.571, "opcount": 7, "soul": 69.66}, "1646215465702.jpg": {"squad": [{"name": "char_151_myrtle", "skill": 1}, {"name": "char_456_ash", "skill": 2}, {"name": "char_401_elysm", "skill": 1}, {"name": "char_103_angel", "skill": 3}, {"name": "char_113_cqbw", "skill": 2}, {"name": "char_311_mudrok", "skill": 2}, {"name": "char_003_kalts", "skill": 3}], "group": 0, "support": {"name": null}, "risk": 18, "avgRarity": 5.571, "opcount": 7, "soul": 72.02}, "1646215791997.jpg": {"squad": [{"name": "char_103_angel", "skill": 3}, {"name": "char_459_tachak", "skill": 2}, {"name": "char_350_surtr", "skill": 3}, {"name": "char_102_texas", "skill": 2}, {"name": "char_151_myrtle", "skill": 1}, {"name": "char_456_ash", "skill": 2}, {"name": "char_458_rfrost", "skill": 2}, {"name": "char_115_headbr", "skill": 2}, {"name": "char_293_thorns", "skill": 3}, {"name": "char_457_blitz", "skill": 2}, {"name": "char_222_bpipe", "skill": 3}, {"name": "char_237_gravel", "skill": 2}, {"name": "char_003_kalts", "skill": 3}], "group": 0, "support": {"name": "char_103_angel", "skill": 3}, "risk": 18, "avgRarity": 5.308, "opcount": 13, "soul": 83.0}, "1646213865770.jpg": {"squad": [{"name": "char_180_amgoat", "skill": 3}, {"name": "char_291_aglina", "skill": 3}, {"name": "char_179_cgbird", "skill": 3}, {"name": "char_358_lisa", "skill": 3}, {"name": "char_340_shwaz", "skill": 3}, {"name": "char_222_bpipe", "skill": 3}, {"name": "char_362_saga", "skill": 3}, {"name": "char_136_hsguma", "skill": 2}, {"name": "char_401_elysm", "skill": 2}, {"name": "char_261_sddrag", "skill": 2}], "group": 0, "support": {"name": "char_180_amgoat", "skill": 3}, "risk": 20, "avgRarity": 5.8, "opcount": 10, "soul": 83.6}, "1646211895961.jpg": {"squad": [{"name": "char_456_ash", "skill": 2}, {"name": "char_151_myrtle", "skill": 1}, {"name": "char_293_thorns", "skill": 3}, {"name": "char_1012_skadi2", "skill": 2}, {"name": "char_003_kalts", "skill": 3}, {"name": "char_363_toddi", "skill": 2}, {"name": "char_222_bpipe", "skill": 2}], "group": 0, "support": {"name": null}, "risk": 18, "avgRarity": 5.571, "opcount": 7, "soul": 72.39}, "1646216959659.jpg": {"squad": [{"name": "char_180_amgoat", "skill": 3}, {"name": "char_284_spot", "skill": 1}, {"name": "char_258_podego", "skill": 2}, {"name": "char_242_otter", "skill": 1}, {"name": "char_181_flower", "skill": 1}, {"name": "char_272_strong", "skill": 2}, {"name": "char_151_myrtle", "skill": 1}], "group": 0, "support": {"name": null}, "duplicate_of": "1646224437733.jpg", "risk": 18, "avgRarity": 4.286, "opcount": 7, "soul": 88.41}, "1646220860129.jpg": {"squad": [{"name": "char_350_surtr", "skill": 3}, {"name": "char_188_helage", "skill": 2}, {"name": "char_474_glady", "skill": 3}, {"name": "char_1001_amiya2", "skill": 1}, {"name": "char_1013_chen2", "skill": 3}, {"name": "char_171_bldsk", "skill": 1}, {"name": "char_151_myrtle", "skill": 1}, {"name": "char_222_bpipe", "skill": 3}, {"name": "char_172_svrash", "skill": 3}, {"name": "char_003_kalts", "skill": 3}, {"name": "char_401_elysm", "skill": 1}, {"name": "char_102_texas", "skill": 2}, {"name": "char_143_ghost", "skill": 2}], "group": 0, "support": {"name": "char_350_surtr", "skill": 3}, "risk": 20, "avgRarity": 5.462, "opcount": 13, "soul": 79.21}, "1646218985564.jpg": {"squad": [{"name": "char_179_cgbird", "skill": 3}, {"name": "char_103_angel", "skill": 3}, {"name": "char_237_gravel", "skill": 2}, {"name": "char_151_myrtle", "skill": 1}, {"name": "char_180_amgoat", "skill": 3}, {"name": "char_003_kalts", "skill": 3}, {"name": "char_226_hmau", "skill": 1}], "group": 0, "support": {"name": null}, "risk": 19, "avgRarity": 5.286, "opcount": 7, "soul": 76.14}, "1646226871131.jpg": {"squad": [{"name": "char_102_texas", "skill": 1}, {"name": "char_2013_cerber", "skill": 2}, {"name": "char_151_myrtle", "skill": 1}, {"name": "char_311_mudrok", "skill": 3}, {"name": "char_128_plosis", "skill": 2}, {"name": "char_180_amgoat", "skill": 3}, {"name": "char_358_lisa", "skill": 3}, {"name": "char_1013_chen2", "skill": 3}, {"name": "char_222_bpipe", "skill": 3}, {"name": "char_179_cgbird", "skill": 3}, {"name": "char_291_aglina", "skill": 2}, {"name": "char_202_demkni", "skill": 3}, {"name": "char_401_elysm", "skill": 2}], "group": 0, "support": {"name": "char_102_texas", "skill": 1}, "risk": 24, "avgRarity": 5.615, "opcount": 13, "soul": 70.62}, "1646224437733.jpg": {"squad": [{"name": "char_378_asbest", "skill": 2}, {"name": "char_003_kalts", "skill": 3}, {"name": "char_258_podego", "skill": 2}, {"name": "char_202_demkni", "skill": 3}, {"name": "char_181_flower", "skill": 1}, {"name": "char_180_amgoat", "skill": 3}, {"name": "char_151_myrtle", "skill": 1}], "group": 0, "support": {"name": null}, "risk": 20, "avgRarity": 5.0, "opcount": 7, "soul": 79.51}, "1646216790244.jpg": {"squad": [{"name": "char_179_cgbird", "skill": 2}, {"name": "char_222_bpipe", "skill": 2}, {"name": "char_1012_skadi2", "skill": 2}, {"name": "char_202_demkni", "skill": 2}, {"name": "char_102_texas", "skill": 2}, {"name": "char_1013_chen2", "skill": 3}, {"name": "char_350_surtr", "skill": 3}, {"name": "char_340_shwaz", "skill": 3}, {"name": "char_264_f12yin", "skill": 2}, {"name": "char_151_myrtle", "skill": 1}], "group": 0, "support": {"name": "char_179_cgbird", "skill": 2}, "risk": 18, "avgRarity": 5.7, "opcount": 10, "soul": 71.69}, "1646230611145.jpg": {"squad": [{"name": "char_237_gravel", "skill": 2}, {"name": "char_376_therex", "skill": 0}, {"name": "char_469_indigo", "skill": 2}, {"name": "char_298_susuro", "skill": 2}, {"name": "char_271_spikes", "skill": 2}, {"name": "char_149_scave", "skill": 2}, {"name": "char_141_nights", "skill": 2}, {"name": "char_440_pinecn", "skill": 1}, {"name": "char_195_glassb", "skill": 2}, {"name": "char_151_myrtle", "skill": 1}, {"name": "char_258_podego", "skill": 2}, {"name": "char_302_glaze", "skill": 2}, {"name": "char_345_folnic", "skill": 2}], "group": 0, "support": {"name": "char_237_gravel", "skill": 2}, "risk": 18, "avgRarity": 3.923, "opcount": 13, "soul": 94.03}, "1646227142631.jpg": {"squad": [{"name": "char_291_aglina", "skill": 3}, {"name": "char_264_f12yin", "skill": 2}, {"name": "char_311_mudrok", "skill": 2}, {"name": "char_151_myrtle", "skill": 1}, {"name": "char_128_plosis", "skill": 2}, {"name": "char_1012_skadi2", "skill": 2}, {"name": "char_180_amgoat", "skill": 3}], "group": 0, "support": {"name": null}, "risk": 18, "avgRarity": 5.571, "opcount": 7, "soul": 72.99}, "1646215926091.jpg": {"squad": [{"name": "char_293_thorns", "skill": 3}, {"name": "char_242_otter", "skill": 2}, {"name": "char_291_aglina", "skill": 3}, {"name": "char_350_surtr", "skill": 3}, {"name": "char_401_elysm", "skill": 1}, {"name": "char_179_cgbird", "skill": 3}, {"name": "char_151_myrtle", "skill": 1}, {"name": "char_144_red", "skill": 2}, {"name": "char_237_gravel", "skill": 2}, {"name": "char_017_huang", "skill": 2}, {"name": "char_003_kalts", "skill": 3}], "group": 0, "support": {"name": "char_293_thorns", "skill": 3}, "risk": 18, "avgRarity": 5.364, "opcount": 11, "soul": 80.95}, "1646233583413.jpg": {"squad": [{"name": "char_180_amgoat", "skill": 3}, {"name": "char_381_bubble", "skill": 2}, {"name": "char_196_sunbr", "skill": 1}, {"name": "char_185_frncat", "skill": 1}, {"name": "char_254_vodfox", "skill": 2}, {"name": "char_501_durin", "skill": 0}, {"name": "char_258_podego", "skill": 2}, {"name": "char_190_clour", "skill": 2}, {"name": "char_281_popka", "skill": 1}, {"name": "char_151_myrtle", "skill": 1}, {"name": "char_117_myrrh", "skill": 1}, {"name": "char_298_susuro", "skill": 2}, {"name": "char_358_lisa", "skill": 2}], "group": 0, "support": {"name": "char_180_amgoat", "skill": 3}, "risk": 19, "avgRarity": 4.154, "opcount": 13, "soul": 92.05}, "1646233229560.jpg": {"squad": [{"name": "char_401_elysm", "skill": 2}, {"name": "char_151_myrtle", "skill": 1}, {"name": "char_1013_chen2", "skill": 3}, {"name": "char_003_kalts", "skill": 3}, {"name": "char_264_f12yin", "skill": 2}, {"name": "char_128_plosis", "skill": 2}, {"name": "char_222_bpipe", "skill": 3}, {"name": "char_311_mudrok", "skill": 2}, {"name": "char_1012_skadi2", "skill": 2}, {"name": "char_103_angel", "skill": 3}], "group": 0, "support": {"name": null}, "risk": 18, "avgRarity": 5.6, "opcount": 10, "soul": 70.86}, "1646221610442.jpg": {"squad": [{"name": "char_264_f12yin", "skill": 2}, {"name": "char_202_demkni", "skill": 2}, {"name": "char_103_angel", "skill": 3}, {"name": "char_102_texas", "skill": 2}, {"name": "char_293_thorns", "skill": 3}, {"name": "char_401_elysm", "skill": 2}, {"name": "char_1012_skadi2", "skill": 2}], "group": 0, "support": {"name": "char_264_f12yin", "skill": 2}, "risk": 18, "avgRarity": 5.714, "opcount": 7, "soul": 79.67}, "1646234304257.jpg": {"squad": [{"name": "char_362_saga", "skill": 3}, {"name": "char_340_shwaz", "skill": 3}, {"name": "char_401_elysm", "skill": 2}, {"name": "char_202_demkni", "skill": 3}, {"name": "char_358_lisa", "skill": 3}, {"name": "char_291_aglina", "skill": 2}, {"name": "char_151_myrtle", "skill": 1}, {"name": "char_350_surtr", "skill": 3}, {"name": "char_179_cgbird", "skill": 3}, {"name": "char_180_amgoat", "skill": 3}, {"name": "char_222_bpipe", "skill": 3}, {"name": "char_1013_chen2", "skill": 3}], "group": 0, "support": {"name": null}, "risk": 23, "avgRarity": 5.75, "opcount": 12, "soul": 70.9}, "1646206425353.jpg": {"squad": [{"name": "char_151_myrtle", "skill": 1}, {"name": "char_179_cgbird", "skill": 3}, {"name": "char_003_kalts", "skill": 3}, {"name": "char_112_siege", "skill": 2}, {"name": "char_202_demkni", "skill": 3}, {"name": "char_291_aglina", "skill": 3}, {"name": "char_222_bpipe", "skill": 3}, {"name": "char_378_asbest", "skill": 2}, {"name": "char_306_leizi", "skill": 2}], "group": 0, "support": {"name": null}, "duplicate_of": "1646238679998.jpg", "risk": 18, "avgRarity": 5.556, "opcount": 9, "soul": 79.78}, "1646237662350.jpg": {"squad": [{"name": "char_340_shwaz", "skill": 3}, {"name": "char_202_demkni", "skill": 3}, {"name": "char_151_myrtle", "skill": 1}, {"name": "char_291_aglina", "skill": 2}, {"name": "char_180_amgoat", "skill": 3}, {"name": "char_350_surtr", "skill": 3}, {"name": "char_102_texas", "skill": 2}, {"name": "char_358_lisa", "skill": 3}, {"name": "char_1013_chen2", "skill": 3}, {"name": "char_222_bpipe", "skill": 3}, {"name": "char_401_elysm", "skill": 2}, {"name": "char_179_cgbird", "skill": 3}, {"name": "char_2015_dusk", "skill": 3}], "group": 0, "support": {"name": "char_340_shwaz", "skill": 3}, "risk": 23, "avgRarity": 5.692, "opcount": 13, "soul": 72.83}, "1646240243850.jpg": {"squad": [{"name": "char_188_helage", "skill": 2}, {"name": "char_401_elysm", "skill": 2}, {"name": "char_362_saga", "skill": 2}, {"name": "char_151_myrtle", "skill": 1}, {"name": "char_254_vodfox", "skill": 2}, {"name": "char_222_bpipe", "skill": 3}, {"name": "char_102_texas", "skill": 2}, {"name": "char_421_crow", "skill": 2}, {"name": "char_456_ash", "skill": 2}], "group": 0, "support": {"name": "char_188_helage", "skill": 2}, "risk": 18, "avgRarity": 5.333, "opcount": 9, "soul": 80.39}, "1646238162621.jpg": {"squad": [{"name": "char_401_elysm", "skill": 2}, {"name": "char_1012_skadi2", "skill": 2}, {"name": "char_181_flower", "skill": 2}, {"name": "char_222_bpipe", "skill": 3}, {"name": "char_293_thorns", "skill": 3}, {"name": "char_148_nearl", "skill": 1}, {"name": "char_151_myrtle", "skill": 1}, {"name": "char_456_ash", "skill": 2}, {"name": "char_188_helage", "skill": 2}, {"name": "char_230_savage", "skill": 1}], "group": 0, "support": {"name": null}, "duplicate_of": "1646244258968.jpg", "risk": 18, "avgRarity": 5.3, "opcount": 10, "soul": 83.29}, "1646236769349.jpg": {"squad": [{"name": "char_003_kalts", "skill": 3}, {"name": "char_222_bpipe", "skill": 2}, {"name": "char_179_cgbird", "skill": 3}, {"name": "char_148_nearl", "skill": 1}, {"name": "char_326_glacus", "skill": 2}, {"name": "char_102_texas", "skill": 2}, {"name": "char_180_amgoat", "skill": 3}], "group": 0, "support": {"name": "char_003_kalts", "skill": 3}, "risk": 19, "avgRarity": 5.571, "opcount": 7, "soul": 82.37}, "1646242905170.jpg": {"squad": [{"name": "char_401_elysm", "skill": 1}, {"name": "char_102_texas", "skill": 2}, {"name": "char_1001_amiya2", "skill": 2}, {"name": "char_147_shining", "skill": 3}, {"name": "char_115_headbr", "skill": 2}, {"name": "char_188_helage", "skill": 2}, {"name": "char_143_ghost", "skill": 2}, {"name": "char_010_chen", "skill": 2}, {"name": "char_416_zumama", "skill": 3}, {"name": "char_456_ash", "skill": 2}, {"name": "char_151_myrtle", "skill": 1}, {"name": "char_222_bpipe", "skill": 3}, {"name": "char_172_svrash", "skill": 3}], "group": 0, "support": {"name": "char_401_elysm", "skill": 1}, "risk": 21, "avgRarity": 5.462, "opcount": 13, "soul": 84.3}, "1646240719810.jpg": {"squad": [{"name": "char_003_kalts", "skill": 3}, {"name": "char_103_angel", "skill": 3}, {"name": "char_311_mudrok", "skill": 3}, {"name": "char_010_chen", "skill": 1}, {"name": "char_102_texas", "skill": 2}, {"name": "char_151_myrtle", "skill": 1}, {"name": "char_365_aprl", "skill": 2}], "group": 0, "support": {"name": "char_003_kalts", "skill": 3}, "risk": 19, "avgRarity": 5.429, "opcount": 7, "soul": 77.88}, "1646245399925.jpg": {"squad": [{"name": "char_197_poca", "skill": 3}, {"name": "char_151_myrtle", "skill": 1}, {"name": "char_222_bpipe", "skill": 3}, {"name": "char_172_svrash", "skill": 3}, {"name": "char_171_bldsk", "skill": 2}, {"name": "char_225_haak", "skill": 3}, {"name": "char_401_elysm", "skill": 2}, {"name": "char_1013_chen2", "skill": 3}, {"name": "char_202_demkni", "skill": 3}, {"name": "char_311_mudrok", "skill": 3}, {"name": "char_102_texas", "skill": 2}, {"name": "char_350_surtr", "skill": 3}], "group": 0, "support": {"name": null}, "risk": 18, "avgRarity": 5.583, "opcount": 12, "soul": 77.05}, "1646244258968.jpg": {"squad": [{"name": "char_401_elysm", "skill": 2}, {"name": "char_456_ash", "skill": 2}, {"name": "char_181_flower", "skill": 2}, {"name": "char_222_bpipe", "skill": 3}, {"name": "char_293_thorns", "skill": 3}, {"name": "char_148_nearl", "skill": 1}, {"name": "char_151_myrtle", "skill": 1}, {"name": "char_1012_skadi2", "skill": 2}, {"name": "char_188_helage", "skill": 2}, {"name": "char_230_savage", "skill": 1}], "group": 0, "support": {"name": null}, "risk": 19, "avgRarity": 5.3, "opcount": 10, "soul": 83.29}, "1646248625295.jpg": {"squad": [{"name": "char_254_vodfox", "skill": 2}, {"name": "char_222_bpipe", "skill": 3}, {"name": "char_128_plosis", "skill": 2}, {"name": "char_2014_nian", "skill": 2}, {"name": "char_243_waaifu", "skill": 1}, {"name": "char_151_myrtle", "skill": 1}, {"name": "char_202_demkni", "skill": 3}, {"name": "char_344_beewax", "skill": 1}, {"name": "char_378_asbest", "skill": 2}, {"name": "char_214_kafka", "skill": 1}, {"name": "char_147_shining", "skill": 3}, {"name": "char_426_billro", "skill": 2}, {"name": "char_416_zumama", "skill": 3}], "group": 0, "support": {"name": "char_254_vodfox", "skill": 2}, "risk": 20, "avgRarity": 5.385, "opcount": 13, "soul": 88.94}, "1646247983052.jpg": {"squad": [{"name": "char_456_ash", "skill": 2}, {"name": "char_1013_chen2", "skill": 3}, {"name": "char_350_surtr", "skill": 3}, {"name": "char_151_myrtle", "skill": 1}, {"name": "char_311_mudrok", "skill": 2}, {"name": "char_401_elysm", "skill": 1}, {"name": "char_1012_skadi2", "skill": 2}, {"name": "char_222_bpipe", "skill": 3}, {"name": "char_180_amgoat", "skill": 3}, {"name": "char_358_lisa", "skill": 2}, {"name": "char_003_kalts", "skill": 3}, {"name": "char_202_demkni", "skill": 1}], "group": 0, "support": {"name": null}, "risk": 20, "avgRarity": 5.75, "opcount": 12, "soul": 64.29}, "1646243012361.jpg": {"squad": [{"name": "char_003_kalts", "skill": 3}, {"name": "char_017_huang", "skill": 2}, {"name": "char_151_myrtle", "skill": 1}, {"name": "char_112_siege", "skill": 2}, {"name": "char_128_plosis", "skill": 2}, {"name": "char_456_ash", "skill": 2}, {"name": "char_144_red", "skill": 2}], "group": 0, "support": {"name": "char_003_kalts", "skill": 3}, "risk": 18, "avgRarity": 5.429, "opcount": 7, "soul": 80.55}, "1646249929339.jpg": {"squad": [{"name": "char_237_gravel", "skill": 1}, {"name": "char_159_peacok", "skill": 1}, {"name": "char_180_amgoat", "skill": 3}, {"name": "char_151_myrtle", "skill": 1}, {"name": "char_258_podego", "skill": 2}, {"name": "char_179_cgbird", "skill": 3}, {"name": "char_326_glacus", "skill": 2}], "group": 0, "support": {"name": null}, "risk": 19, "avgRarity": 4.714, "opcount": 7, "soul": 83.83}, "1646246362063.jpg": {"squad": [{"name": "char_214_kafka", "skill": 1}, {"name": "char_416_zumama", "skill": 3}, {"name": "char_237_gravel", "skill": 2}, {"name": "char_151_myrtle", "skill": 1}, {"name": "char_437_mizuki", "skill": 1}, {"name": "char_197_poca", "skill": 3}, {"name": "char_222_bpipe", "skill": 3}, {"name": "char_456_ash", "skill": 2}, {"name": "char_474_glady", "skill": 2}, {"name": "char_102_texas", "skill": 2}, {"name": "char_350_surtr", "skill": 3}, {"name": "char_003_kalts", "skill": 3}, {"name": "char_426_billro", "skill": 3}], "group": 0, "support": {"name": "char_214_kafka", "skill": 1}, "risk": 18, "avgRarity": 5.538, "opcount": 13, "soul": 84.4}, "1646238679998.jpg": {"squad": [{"name": "char_003_kalts", "skill": 3}, {"name": "char_179_cgbird", "skill": 3}, {"name": "char_204_platnm", "skill": 2}, {"name": "char_222_bpipe", "skill": 3}, {"name": "char_151_myrtle", "skill": 1}, {"name": "char_378_asbest", "skill": 2}, {"name": "char_306_leizi", "skill": 2}], "group": 0, "support": {"name": "char_003_kalts", "skill": 3}, "risk": 18, "avgRarity": 5.286, "opcount": 7, "soul": 81.71}, "1646235273373.jpg": {"squad": [{"name": "char_456_ash", "skill": 2}, {"name": "char_102_texas", "skill": 2}, {"name": "char_1012_skadi2", "skill": 2}, {"name": "char_115_headbr", "skill": 2}, {"name": "char_457_blitz", "skill": 2}, {"name": "char_179_cgbird", "skill": 2}, {"name": "char_003_kalts", "skill": 3}], "group": 0, "support": {"name": "char_456_ash", "skill": 2}, "risk": 18, "avgRarity": 5.571, "opcount": 7, "soul": 81.82}}